<S:Envelope xmlns:S="http://schemas.xmlsoap.org/soap/envelope/" xmlns:SOAP-ENV="http://schemas.xmlsoap.org/soap/envelope/" xmlns:wsse="http://docs.oasis-open.org/wss/2004/01/oasis-200401-wss-wssecurity-secext-1.0.xsd">
    <S:Body>
        <ns2:getCatalogListResponse xmlns:ns2="http://ehd.mos.com/">
            <ns2:ehdCatalogs>
                <ns2:ehdCatalog>
                    <ns2:id>6401</ns2:id>
                    <ns2:fullName>Станции Московского метрополитена</ns2:fullName>
                    <ns2:technicalName>Станции Московского метрополитена</ns2:technicalName>
                    <ns2:shortName>Станции Московского метрополитена</ns2:shortName>
                    <ns2:accountingObject>Станции Московского метрополитена</ns2:accountingObject>
                    <ns2:keywords>метро, станции</ns2:keywords>
                    <ns2:vid>Справочник (основные атрибуты объекта)</ns2:vid>
                    <ns2:type>Городской межотраслевой (межведомственный)</ns2:type>
                    <ns2:period>По мере поступления изменений из источников актуализации</ns2:period>
                    <ns2:hasGeo>false</ns2:hasGeo>
                    <ns2:categories>Справочная информация</ns2:categories>
                    <ns2:oiv>Департамент транспорта и развития дорожно-транспортной инфраструктуры города Москвы</ns2:oiv>
                </ns2:ehdCatalog>
                <ns2:ehdCatalog>
                    <ns2:id>7668</ns2:id>
                    <ns2:fullName>Линии Московского метрополитена</ns2:fullName>
                    <ns2:technicalName>Линии Московского метрополитена</ns2:technicalName>
                    <ns2:shortName>Линии Московского метрополитена</ns2:shortName>
                    <ns2:accountingObject>Линии Московского метрополитена</ns2:accountingObject>
                    <ns2:keywords>Линии Московского метрополитена</ns2:keywords>
                    <ns2:vid>Справочник (основные атрибуты объекта)</ns2:vid>
                    <ns2:type>Городской межотраслевой (межведомственный)</ns2:type>
                    <ns2:period>По мере поступления изменений из источников актуализации</ns2:period>
                    <ns2:hasGeo>false</ns2:hasGeo>
                    <ns2:categories>Справочная информация</ns2:categories>
                    <ns2:oiv>Департамент транспорта и развития дорожно-транспортной инфраструктуры города Москвы</ns2:oiv>
                </ns2:ehdCatalog>
                <ns2:ehdCatalog>
                    <ns2:id>27451</ns2:id>
                    <ns2:fullName>Адресный реестр объектов недвижимости города Москвы</ns2:fullName>
                    <ns2:technicalName>Адресный реестр объектов недвижимости города Москвы</ns2:technicalName>
                    <ns2:shortName>Адресный реестр объектов недвижимости города Москвы</ns2:shortName>
                    <ns2:accountingObject>Адресная информация о земельных участках, зданиях, сооружениях, объектах незавершенного строительства и помещениях, расположенных в пределах установленных границ города Москвы</ns2:accountingObject>
                    <ns2:keywords>адрес, здание, сооружение, адресный реестр, объект незавершенного строительства, АР</ns2:keywords>
                    <ns2:vid>Справочник (основные атрибуты объекта)</ns2:vid>
                    <ns2:type>Городской межотраслевой (межведомственный)</ns2:type>
                    <ns2:period>Настраиваемая (Произвольный срок)</ns2:period>
                    <ns2:hasGeo>true</ns2:hasGeo>
                    <ns2:categories>Земля и имущество</ns2:categories>
                    <ns2:oiv>Департамент городского имущества города Москвы</ns2:oiv>
                </ns2:ehdCatalog>
                <ns2:ehdCatalog>
                    <ns2:id>27455</ns2:id>
                    <ns2:fullName>Кадастровый номер объекта недвижимости (кроме земельного участка)</ns2:fullName>
                    <ns2:technicalName>Кадастровый номер объекта недвижимости (кроме земельного участка)</ns2:technicalName>
                    <ns2:shortName>Кадастровый номер объекта недвижимости (кроме земельного участка)</ns2:shortName>
                    <ns2:accountingObject>Адресная информация о земельных участках, зданиях, сооружениях, объектах незавершенного строительства и помещениях, расположенных в пределах установленных границ города Москвы</ns2:accountingObject>
                    <ns2:keywords>адрес, здание, сооружение, адресный реестр, объект незавершенного строительства, АР</ns2:keywords>
                    <ns2:vid>Справочник (дополнительные атрибуты)</ns2:vid>
                    <ns2:type>Городской межотраслевой (межведомственный)</ns2:type>
                    <ns2:period>Настраиваемая (Произвольный срок)</ns2:period>
                    <ns2:hasGeo>false</ns2:hasGeo>
                    <ns2:categories>Земля и имущество</ns2:categories>
                    <ns2:oiv>Департамент городского имущества города Москвы</ns2:oiv>
                </ns2:ehdCatalog>
                <ns2:ehdCatalog>
                    <ns2:id>27456</ns2:id>
                    <ns2:fullName>Кадастровый номер земельного участка (для ОКС)</ns2:fullName>
                    <ns2:technicalName>Кадастровый номер земельного участка (для ОКС)</ns2:technicalName>
                    <ns2:shortName>Кадастровый номер земельного участка (для ОКС)</ns2:shortName>
                    <ns2:accountingObject>Адресная информация о земельных участках, зданиях, сооружениях, объектах незавершенного строительства и помещениях, расположенных в пределах установленных границ города Москвы</ns2:accountingObject>
                    <ns2:keywords>адрес, здание, сооружение, адресный реестр, объект незавершенного строительства, АР</ns2:keywords>
                    <ns2:vid>Справочник (дополнительные атрибуты)</ns2:vid>
                    <ns2:type>Городской межотраслевой (межведомственный)</ns2:type>
                    <ns2:period>Настраиваемая (Произвольный срок)</ns2:period>
                    <ns2:hasGeo>false</ns2:hasGeo>
                    <ns2:categories>Земля и имущество</ns2:categories>
                    <ns2:oiv>Департамент городского имущества города Москвы</ns2:oiv>
                </ns2:ehdCatalog>
                <ns2:ehdCatalog>
                    <ns2:id>28439</ns2:id>
                    <ns2:fullName>БТИ. Адресный реестр</ns2:fullName>
                    <ns2:technicalName>БТИ. Адресный реестр</ns2:technicalName>
                    <ns2:shortName>Адресный реестр</ns2:shortName>
                    <ns2:accountingObject></ns2:accountingObject>
                    <ns2:keywords></ns2:keywords>
                    <ns2:vid>Справочник (основные атрибуты объекта)</ns2:vid>
                    <ns2:type>Городской межотраслевой (межведомственный)</ns2:type>
                    <ns2:period>Ежемесячно</ns2:period>
                    <ns2:hasGeo>false</ns2:hasGeo>
                    <ns2:categories>Имущество и земля города Москвы</ns2:categories>
                    <ns2:oiv>Департамент городского имущества города Москвы</ns2:oiv>
                </ns2:ehdCatalog>
                <ns2:ehdCatalog>
                    <ns2:id>28475</ns2:id>
                    <ns2:fullName>Дополнение к Адресному реестру объектов недвижимости города Москвы</ns2:fullName>
                    <ns2:technicalName>Дополнение к Адресному реестру объектов недвижимости города Москвы</ns2:technicalName>
                    <ns2:shortName>Дополнение к Адресному реестру объектов недвижимости города Москвы</ns2:shortName>
                    <ns2:accountingObject>Не вошедшая в Адресный реестр объектов недвижимости города Москвы Адресная информация о зданиях, сооружениях, объектах незавершенного строительства и помещениях, расположенных в пределах установленных границ города Москвы.</ns2:accountingObject>
                    <ns2:keywords>адрес, здание, сооружение, адресный реестр, объект незавершенного строительства, АР, дополнение к АР, госуслуги</ns2:keywords>
                    <ns2:vid>Справочник (основные атрибуты объекта)</ns2:vid>
                    <ns2:type>Городской межотраслевой (межведомственный)</ns2:type>
                    <ns2:period>Настраиваемая (Произвольный срок)</ns2:period>
                    <ns2:hasGeo>false</ns2:hasGeo>
                    <ns2:categories>Земля и имущество</ns2:categories>
                    <ns2:oiv>Департамент городского имущества города Москвы</ns2:oiv>
                </ns2:ehdCatalog>
                <ns2:ehdCatalog>
                    <ns2:id>28476</ns2:id>
                    <ns2:fullName>Кадастровый номер объекта недвижимости (кроме земельного участка)_copy1</ns2:fullName>
                    <ns2:technicalName>Кадастровый номер объекта недвижимости (кроме земельного участка)_copy1</ns2:technicalName>
                    <ns2:shortName>Кадастровый номер объекта недвижимости (кроме земельного участка)_copy1</ns2:shortName>
                    <ns2:accountingObject>Не вошедшая в Адресный реестр объектов недвижимости города Москвы Адресная информация о зданиях, сооружениях, объектах незавершенного строительства и помещениях, расположенных в пределах установленных границ города Москвы.</ns2:accountingObject>
                    <ns2:keywords>адрес, здание, сооружение, адресный реестр, объект незавершенного строительства, АР, дополнение к АР, госуслуги</ns2:keywords>
                    <ns2:vid>Справочник (дополнительные атрибуты)</ns2:vid>
                    <ns2:type>Городской межотраслевой (межведомственный)</ns2:type>
                    <ns2:period>Настраиваемая (Произвольный срок)</ns2:period>
                    <ns2:hasGeo>false</ns2:hasGeo>
                    <ns2:categories>Земля и имущество</ns2:categories>
                    <ns2:oiv>Департамент городского имущества города Москвы</ns2:oiv>
                </ns2:ehdCatalog>
                <ns2:ehdCatalog>
                    <ns2:id>28477</ns2:id>
                    <ns2:fullName>Кадастровый номер земельного участка (для ОКС)_copy1</ns2:fullName>
                    <ns2:technicalName>Кадастровый номер земельного участка (для ОКС)_copy1</ns2:technicalName>
                    <ns2:shortName>Кадастровый номер земельного участка (для ОКС)_copy1</ns2:shortName>
                    <ns2:accountingObject>Не вошедшая в Адресный реестр объектов недвижимости города Москвы Адресная информация о зданиях, сооружениях, объектах незавершенного строительства и помещениях, расположенных в пределах установленных границ города Москвы.</ns2:accountingObject>
                    <ns2:keywords>адрес, здание, сооружение, адресный реестр, объект незавершенного строительства, АР, дополнение к АР, госуслуги</ns2:keywords>
                    <ns2:vid>Справочник (дополнительные атрибуты)</ns2:vid>
                    <ns2:type>Городской межотраслевой (межведомственный)</ns2:type>
                    <ns2:period>Настраиваемая (Произвольный срок)</ns2:period>
                    <ns2:hasGeo>false</ns2:hasGeo>
                    <ns2:categories>Земля и имущество</ns2:categories>
                    <ns2:oiv>Департамент городского имущества города Москвы</ns2:oiv>
                </ns2:ehdCatalog>
                <ns2:ehdCatalog>
                    <ns2:id>28506</ns2:id>
                    <ns2:fullName>БТИ. Классификатор улиц</ns2:fullName>
                    <ns2:technicalName>БТИ. Классификатор улиц</ns2:technicalName>
                    <ns2:shortName>Классификатор улиц</ns2:shortName>
                    <ns2:accountingObject>Сведения жилого и нежилого фондов города Москвы</ns2:accountingObject>
                    <ns2:keywords>фонд, жилой фонд, нежилой фонд, адрес, здание, сооружение, строение, помещение, квартира, комната, инвентаризационно-технические характеристики, инвентаризация</ns2:keywords>
                    <ns2:vid>Справочник (основные атрибуты объекта)</ns2:vid>
                    <ns2:type>Городской межотраслевой (межведомственный)</ns2:type>
                    <ns2:period>Ежемесячно</ns2:period>
                    <ns2:hasGeo>false</ns2:hasGeo>
                    <ns2:categories>Земля и имущество</ns2:categories>
                    <ns2:oiv>Департамент городского имущества города Москвы</ns2:oiv>
                </ns2:ehdCatalog>
                <ns2:ehdCatalog>
                    <ns2:id>28507</ns2:id>
                    <ns2:fullName>БТИ. Классификатор административных округов</ns2:fullName>
                    <ns2:technicalName>БТИ. Классификатор административных округов</ns2:technicalName>
                    <ns2:shortName>Классификатор административных округов</ns2:shortName>
                    <ns2:accountingObject>Сведения жилого и нежилого фондов города Москвы</ns2:accountingObject>
                    <ns2:keywords>фонд, жилой фонд, нежилой фонд, адрес, здание, сооружение, строение, помещение, квартира, комната, инвентаризационно-технические характеристики, инвентаризация</ns2:keywords>
                    <ns2:vid>Справочник (основные атрибуты объекта)</ns2:vid>
                    <ns2:type>Городской отраслевой (ведомственный)</ns2:type>
                    <ns2:period>По мере поступления изменений из источников актуализации</ns2:period>
                    <ns2:hasGeo>false</ns2:hasGeo>
                    <ns2:categories>Земля и имущество</ns2:categories>
                    <ns2:oiv>Департамент городского имущества города Москвы</ns2:oiv>
                </ns2:ehdCatalog>
                <ns2:ehdCatalog>
                    <ns2:id>28508</ns2:id>
                    <ns2:fullName>БТИ. Классификатор районов</ns2:fullName>
                    <ns2:technicalName>БТИ. Классификатор районов</ns2:technicalName>
                    <ns2:shortName>Классификатор районов</ns2:shortName>
                    <ns2:accountingObject>Сведения жилого и нежилого фондов города Москвы</ns2:accountingObject>
                    <ns2:keywords>фонд, жилой фонд, нежилой фонд, адрес, здание, сооружение, строение, помещение, квартира, комната, инвентаризационно-технические характеристики, инвентаризация</ns2:keywords>
                    <ns2:vid>Справочник (основные атрибуты объекта)</ns2:vid>
                    <ns2:type>Городской отраслевой (ведомственный)</ns2:type>
                    <ns2:period>По мере поступления изменений из источников актуализации</ns2:period>
                    <ns2:hasGeo>false</ns2:hasGeo>
                    <ns2:categories>Земля и имущество</ns2:categories>
                    <ns2:oiv>Департамент городского имущества города Москвы</ns2:oiv>
                </ns2:ehdCatalog>
                <ns2:ehdCatalog>
                    <ns2:id>28627</ns2:id>
                    <ns2:fullName>ФИАС. Номера домов</ns2:fullName>
                    <ns2:technicalName>ФИАС. Номера домов</ns2:technicalName>
                    <ns2:shortName>Государственный адресный реестр ФИАС</ns2:shortName>
                    <ns2:accountingObject>Сведения об адресах и о реквизитах документов о присвоении, об изменении, аннулировании адреса.</ns2:accountingObject>
                    <ns2:keywords>адрес, интервал, дом, местоположение, адресообразующий элемент, район, город, регион, округ</ns2:keywords>
                    <ns2:vid>Справочник (основные атрибуты объекта)</ns2:vid>
                    <ns2:type>Федеральный отраслевой (ведомственный)</ns2:type>
                    <ns2:period>По мере поступления изменений из источников актуализации</ns2:period>
                    <ns2:hasGeo>false</ns2:hasGeo>
                    <ns2:categories>Справочники АС УР</ns2:categories>
                    <ns2:oiv>Департамент информационных технологий города Москвы</ns2:oiv>
                </ns2:ehdCatalog>
                <ns2:ehdCatalog>
                    <ns2:id>29690</ns2:id>
                    <ns2:fullName>Дополнение к Адресному реестру объектов недвижимости города Москвы для оказания государственных услуг в электронном виде</ns2:fullName>
                    <ns2:technicalName>Дополнение к Адресному реестру объектов недвижимости города Москвы для оказания государственных услуг в электронном виде</ns2:technicalName>
                    <ns2:shortName>Дополнение к Адресному реестру объектов недвижимости города Москвы для оказания государственных услуг в электронном виде</ns2:shortName>
                    <ns2:accountingObject>Не вошедшая в Адресный реестр объектов недвижимости города Москвы Адресная информация о зданиях, сооружениях, объектах незавершенного строительства и помещениях, расположенных в пределах установленных границ города Москвы.</ns2:accountingObject>
                    <ns2:keywords>адрес, здание, сооружение, адресный реестр, объект незавершенного строительства, АР, дополнение к АР, госуслуги</ns2:keywords>
                    <ns2:vid>Справочник (основные атрибуты объекта)</ns2:vid>
                    <ns2:type>Городской межотраслевой (межведомственный)</ns2:type>
                    <ns2:period>Настраиваемая (Произвольный срок)</ns2:period>
                    <ns2:hasGeo>false</ns2:hasGeo>
                    <ns2:categories>Земля и имущество</ns2:categories>
                    <ns2:oiv>Департамент городского имущества города Москвы</ns2:oiv>
                </ns2:ehdCatalog>
                <ns2:ehdCatalog>
                    <ns2:id>29691</ns2:id>
                    <ns2:fullName>Кадастровый номер объекта недвижимости (кроме земельного участка)_copy1_copy1</ns2:fullName>
                    <ns2:technicalName>Кадастровый номер объекта недвижимости (кроме земельного участка)_copy1_copy1</ns2:technicalName>
                    <ns2:shortName>Кадастровый номер объекта недвижимости (кроме земельного участка)_copy1_copy1</ns2:shortName>
                    <ns2:accountingObject>Не вошедшая в Адресный реестр объектов недвижимости города Москвы Адресная информация о зданиях, сооружениях, объектах незавершенного строительства и помещениях, расположенных в пределах установленных границ города Москвы.</ns2:accountingObject>
                    <ns2:keywords>адрес, здание, сооружение, адресный реестр, объект незавершенного строительства, АР, дополнение к АР, госуслуги</ns2:keywords>
                    <ns2:vid>Справочник (дополнительные атрибуты)</ns2:vid>
                    <ns2:type>Городской межотраслевой (межведомственный)</ns2:type>
                    <ns2:period>Настраиваемая (Произвольный срок)</ns2:period>
                    <ns2:hasGeo>false</ns2:hasGeo>
                    <ns2:categories>Земля и имущество</ns2:categories>
                    <ns2:oiv>Департамент городского имущества города Москвы</ns2:oiv>
                </ns2:ehdCatalog>
                <ns2:ehdCatalog>
                    <ns2:id>29692</ns2:id>
                    <ns2:fullName>Кадастровый номер земельного участка (для ОКС)_copy1_copy1</ns2:fullName>
                    <ns2:technicalName>Кадастровый номер земельного участка (для ОКС)_copy1_copy1</ns2:technicalName>
                    <ns2:shortName>Кадастровый номер земельного участка (для ОКС)_copy1_copy1</ns2:shortName>
                    <ns2:accountingObject>Не вошедшая в Адресный реестр объектов недвижимости города Москвы Адресная информация о зданиях, сооружениях, объектах незавершенного строительства и помещениях, расположенных в пределах установленных границ города Москвы.</ns2:accountingObject>
                    <ns2:keywords>адрес, здание, сооружение, адресный реестр, объект незавершенного строительства, АР, дополнение к АР, госуслуги</ns2:keywords>
                    <ns2:vid>Справочник (дополнительные атрибуты)</ns2:vid>
                    <ns2:type>Городской межотраслевой (межведомственный)</ns2:type>
                    <ns2:period>Настраиваемая (Произвольный срок)</ns2:period>
                    <ns2:hasGeo>false</ns2:hasGeo>
                    <ns2:categories>Земля и имущество</ns2:categories>
                    <ns2:oiv>Департамент городского имущества города Москвы</ns2:oiv>
                </ns2:ehdCatalog>
            </ns2:ehdCatalogs>
        </ns2:getCatalogListResponse>
    </S:Body>
</S:Envelope>